LICENSE
MANIFEST.in
README.md
requirements.txt
setup.py
biasprobe/__init__.py
biasprobe/_version.py
biasprobe/data.py
biasprobe/extract.py
biasprobe/hook.py
biasprobe/probe.py
biasprobe/prompt.py
biasprobe/runner.py
biasprobe/serializable.py
biasprobe.egg-info/PKG-INFO
biasprobe.egg-info/SOURCES.txt
biasprobe.egg-info/dependency_links.txt
biasprobe.egg-info/requires.txt
biasprobe.egg-info/top_level.txt